vecy-0.1.0.dist-info/METADATA
vecy-0.1.0.dist-info/WHEEL
vecy/__init__.py
vecy/vecy.cpython-311-darwin.so
vecy-0.1.0.dist-info/RECORD
