Metadata-Version: 2.1
Name: vecy
Version: 0.1.0
